eshare/__init__.py
eshare/app.py
eshare/encryption.py
eshare/sharing.py
eshare/utils.py
eshare-1.0.0.dist-info/METADATA
eshare-1.0.0.dist-info/WHEEL
eshare-1.0.0.dist-info/entry_points.txt
eshare-1.0.0.dist-info/top_level.txt
eshare-1.0.0.dist-info/RECORD
