Metadata-Version: 2.1
Name: eshare
Version: 1.0.0
Summary: Encrypted File Sharing Command-Line Tool
Home-page: https://github.com/imparth7/eshare
Author: Parth Dudhatra
Author-email: imparth.dev@gmail.com
License: MIT
Keywords: encryption,file-sharing,cli,secure,python,password,cryptography
Platform: Any
Classifier: Programming Language :: Python :: 3
Classifier: License :: OSI Approved :: MIT License
Classifier: Operating System :: OS Independent
Requires-Python: >=3.6
Requires-Dist: cryptography==41.0.0
Requires-Dist: typer==0.9.0
Requires-Dist: bcrypt==4.0.1
